pypole/__init__.py
pypole/compute.py
pypole/convert.py
pypole/dipole.py
pypole/example.py
pypole/fit.py
pypole/maps.py
pypole/plotting.py
pypole-0.1.1.dist-info/entry_points.txt
pypole-0.1.1.dist-info/LICENSE
pypole-0.1.1.dist-info/WHEEL
pypole-0.1.1.dist-info/METADATA
pypole-0.1.1.dist-info/RECORD
