Metadata-Version: 2.1
Name: pypole
Version: 0.1.1
Summary: Awesome `pypole` is a Python cli/package created with https://github.com/TezRomacH/python-package-template
Home-page: https://github.com/pypole/pypole
License: MIT
Author: pypole
Author-email: michaelvolk1979@gmail.com
Requires-Python: >=3.9,<4.0
Classifier: Development Status :: 3 - Alpha
Classifier: Intended Audience :: Education
Classifier: License :: OSI Approved :: MIT License
Classifier: Operating System :: OS Independent
Classifier: Programming Language :: Python :: 3
Classifier: Programming Language :: Python :: 3.9
Classifier: Programming Language :: Python :: 3.10
Classifier: Programming Language :: Python :: 3.11
Classifier: Programming Language :: Python :: 3
Classifier: Programming Language :: Python :: 3.9
Classifier: Topic :: Scientific/Engineering :: Physics
Requires-Dist: matplotlib (>=3.6.2,<4.0.0)
Requires-Dist: numba (>=0.56.4,<0.57.0)
Requires-Dist: numpy (>=1.23.4,<2.0.0)
Requires-Dist: pre-commit (>=2.20.0,<3.0.0)
Requires-Dist: rich (>=10.14.0,<11.0.0)
Requires-Dist: scipy (>=1.9.3,<2.0.0)
Requires-Dist: tqdm (>=4.64.1,<5.0.0)
Project-URL: Repository, https://github.com/pypole/pypole
